goto_plus/__init__.py
goto_plus/goto.py
goto_plus-0.0.1.dist-info/METADATA
goto_plus-0.0.1.dist-info/WHEEL
goto_plus-0.0.1.dist-info/top_level.txt
goto_plus-0.0.1.dist-info/RECORD
