Metadata-Version: 2.1
Name: goto-plus
Version: 0.0.1
Summary: UNKNOWN
Home-page: https://github.com/abhinav-gg/GoTo-Python/
Author: Abhinav G
Author-email: agupta.cam7@gmail.com
License: MIT
Keywords: goto,python,line,execution,procedure,pygoto,goto-line,line number,exec,file
Platform: UNKNOWN
Classifier: Programming Language :: Python :: 3
Classifier: License :: OSI Approved :: MIT License
Classifier: Operating System :: OS Independent
